sdm_reference_model/__init__.py
sdm_reference_model/change_scenario.py
sdm_reference_model/distribution.py
sdm_reference_model/matcher.py
sdm_reference_model/order.py
sdm_reference_model/performance.py
sdm_reference_model/procedure.py
sdm_reference_model/processes.py
sdm_reference_model/product.py
sdm_reference_model/reference_model.py
sdm_reference_model/resources.py
sdm_reference_model-0.1.9.dist-info/LICENSE
sdm_reference_model-0.1.9.dist-info/METADATA
sdm_reference_model-0.1.9.dist-info/WHEEL
sdm_reference_model-0.1.9.dist-info/RECORD
