Metadata-Version: 2.1
Name: sdm-reference-model
Version: 0.1.9
Summary: 
Author: Sebastian Behrendt
Author-email: sebastianbehrendt97@gmail.com
Requires-Python: >=3.10,<4.0
Classifier: Programming Language :: Python :: 3
Classifier: Programming Language :: Python :: 3.10
Classifier: Programming Language :: Python :: 3.11
Requires-Dist: aas-middleware (>=0.2.3,<0.3.0)
Requires-Dist: importlib-metadata (>=8.5.0,<9.0.0)
